{"_id":{"$oid":"5b9d955612e60c789e7cef84"},"userId":"5b9d9549f93b5650885e49b4","__v":{"$numberInt":"0"},"key":"a1ab2736-01b4-498f-8a80-14df6a652a68"}
{"_id":{"$oid":"5b9eb88912e60c789e7d0690"},"userId":"5b9eb877339435359cbbe521","__v":{"$numberInt":"0"},"key":"e51bacfd-7345-42c0-b5ec-91e2ee6068ea"}
{"_id":{"$oid":"5ba615831fe6e3161bdbe3fe"},"userId":"5b9d24cb5a06bc1e8cf5f9ec","__v":{"$numberInt":"0"},"key":"ff2e1a12-0e15-44e5-8995-36d7fff9cf40"}
{"_id":{"$oid":"5ba6bd1c1fe6e3161bdc08ad"},"userId":"5ba6bcaa6c696714401c2f02","__v":{"$numberInt":"0"},"key":"0240f43e-f837-4bea-8b7f-8b4b72beda25"}
{"_id":{"$oid":"5ba6c5dd1fe6e3161bdc188c"},"userId":"5ba6c58726a55f3968cb9e8e","__v":{"$numberInt":"0"},"key":"a7b0fce4-017f-48d6-b5d9-7ee6da50ecbf"}
